spruce/__init__.py
spruce/cli.py
spruce_compiler-0.1.0.dist-info/licenses/LICENSE
spruce_compiler-0.1.0.dist-info/METADATA
spruce_compiler-0.1.0.dist-info/WHEEL
spruce_compiler-0.1.0.dist-info/entry_points.txt
spruce_compiler-0.1.0.dist-info/top_level.txt
spruce_compiler-0.1.0.dist-info/RECORD
